erf/__init__.py
erf/test.py
erf-0.1.3.dist-info/METADATA
erf-0.1.3.dist-info/WHEEL
erf-0.1.3.dist-info/top_level.txt
erf-0.1.3.dist-info/RECORD
